django_elasticsearch_dsl/__init__.py
django_elasticsearch_dsl/apps.py
django_elasticsearch_dsl/documents.py
django_elasticsearch_dsl/exceptions.py
django_elasticsearch_dsl/fields.py
django_elasticsearch_dsl/indices.py
django_elasticsearch_dsl/models.py
django_elasticsearch_dsl/registries.py
django_elasticsearch_dsl/search.py
django_elasticsearch_dsl/signals.py
django_elasticsearch_dsl/management/__init__.py
django_elasticsearch_dsl/management/commands/__init__.py
django_elasticsearch_dsl/management/commands/search_index.py
django_elasticsearch_dsl/test/__init__.py
django_elasticsearch_dsl/test/testcases.py
django_elasticsearch_dsl-8.1.dist-info/licenses/AUTHORS.rst
django_elasticsearch_dsl-8.1.dist-info/licenses/LICENSE
django_elasticsearch_dsl-8.1.dist-info/METADATA
django_elasticsearch_dsl-8.1.dist-info/WHEEL
django_elasticsearch_dsl-8.1.dist-info/top_level.txt
django_elasticsearch_dsl-8.1.dist-info/RECORD
