Metadata-Version: 2.4
Name: django-elasticsearch-dsl
Version: 8.1
Summary: Wrapper around elasticsearch-dsl-py for django models
Home-page: https://github.com/sabricot/django-elasticsearch-dsl
Author: Sabricot
License: Apache Software License 2.0
Keywords: django elasticsearch elasticsearch-dsl
Classifier: Development Status :: 3 - Alpha
Classifier: Framework :: Django
Classifier: Framework :: Django :: 3.2
Classifier: Framework :: Django :: 4.1
Classifier: Framework :: Django :: 4.2
Classifier: Intended Audience :: Developers
Classifier: License :: OSI Approved :: BSD License
Classifier: Natural Language :: English
Classifier: Programming Language :: Python :: 3
Classifier: Programming Language :: Python :: 3.8
Classifier: Programming Language :: Python :: 3.9
Classifier: Programming Language :: Python :: 3.10
Classifier: Programming Language :: Python :: 3.11
Requires-Python: >=3.8
License-File: LICENSE
License-File: AUTHORS.rst
Requires-Dist: elasticsearch-dsl<=8.17.1,>=8.9.0
Requires-Dist: six
Provides-Extra: celery
Requires-Dist: celery>=4.1.0; extra == "celery"
Dynamic: author
Dynamic: classifier
Dynamic: description
Dynamic: home-page
Dynamic: keywords
Dynamic: license
Dynamic: license-file
Dynamic: provides-extra
Dynamic: requires-dist
Dynamic: requires-python
Dynamic: summary
